say11/cli.py
say11-0.1.0.dist-info/LICENSE
say11-0.1.0.dist-info/METADATA
say11-0.1.0.dist-info/WHEEL
say11-0.1.0.dist-info/entry_points.txt
say11-0.1.0.dist-info/RECORD
